streamlit_option_menu/__init__.py
streamlit_option_menu/frontend/dist/index.html
streamlit_option_menu/frontend/dist/css/app.1b9a5a45.css
streamlit_option_menu/frontend/dist/css/chunk-vendors.083b1cc7.css
streamlit_option_menu/frontend/dist/fonts/bootstrap-icons.ba49e844.woff
streamlit_option_menu/frontend/dist/fonts/bootstrap-icons.cc1e5eda.woff2
streamlit_option_menu/frontend/dist/js/app.107b8ce3.js
streamlit_option_menu/frontend/dist/js/app.107b8ce3.js.map
streamlit_option_menu/frontend/dist/js/chunk-vendors.f4d7cdd3.js
streamlit_option_menu/frontend/dist/js/chunk-vendors.f4d7cdd3.js.map
streamlit_option_menu-0.4.0.dist-info/LICENSE
streamlit_option_menu-0.4.0.dist-info/METADATA
streamlit_option_menu-0.4.0.dist-info/WHEEL
streamlit_option_menu-0.4.0.dist-info/top_level.txt
streamlit_option_menu-0.4.0.dist-info/RECORD
